[
  {
    "key": "Home",
    "url": "/",
    "children": []
  },
  {
    "key": "About Us",
    "url": "/about/",
    "children": []
  },
  {
    "key": "Projects",
    "url": "/projects/",
    "children": [
      {
        "key": "Project 1",
        "url": "/projects/project-1/"
      },
      {
        "key": "Project 2",
        "url": "/projects/project-2/"
      }
    ]
  },
  {
    "key": "Services",
    "url": "/services/",
    "children": []
  },
  {
    "key": "Service Areas",
    "url": "/service-areas/",
    "children": [
      { "key": "Pulaski, TN", "url": "/service-areas/pulaski-tn/" },
      { "key": "Athens, AL", "url": "/service-areas/athens-al/" }
    ]
  }
]
